kroki/__init__.py
kroki/cache.py
kroki/client.py
kroki/common.py
kroki/config.py
kroki/diagram_types.py
kroki/logging.py
kroki/parsing.py
kroki/plugin.py
kroki/render.py
mkdocs_kroki_plugin-1.1.0.dist-info/METADATA
mkdocs_kroki_plugin-1.1.0.dist-info/WHEEL
mkdocs_kroki_plugin-1.1.0.dist-info/entry_points.txt
mkdocs_kroki_plugin-1.1.0.dist-info/licenses/LICENSE
mkdocs_kroki_plugin-1.1.0.dist-info/RECORD
