Metadata-Version: 2.4
Name: mkdocs-kroki-plugin
Version: 1.1.0
Summary: MkDocs plugin for Kroki-Diagrams
Project-URL: Documentation, https://github.com/AVATEAM-IT-SYSTEMHAUS/mkdocs-kroki-plugin#readme
Project-URL: Issues, https://github.com/AVATEAM-IT-SYSTEMHAUS/mkdocs-kroki-plugin/issues
Project-URL: Source, https://github.com/AVATEAM-IT-SYSTEMHAUS/mkdocs-kroki-plugin
Author-email: Timo Reymann <mail@timo-reymann.de>, Antonia Siegert <oniboni@mailbox.org>, Benjamin Bittner <benjamin.bittner@avateam.com>
License-Expression: MIT
License-File: LICENSE
Keywords: diagram,kroki,markdown,mkdocs,python
Classifier: Development Status :: 4 - Beta
Classifier: Framework :: MkDocs
Classifier: Intended Audience :: Developers
Classifier: Intended Audience :: Information Technology
Classifier: Intended Audience :: Science/Research
Classifier: License :: OSI Approved :: MIT License
Classifier: Programming Language :: Python
Classifier: Programming Language :: Python :: 3 :: Only
Classifier: Programming Language :: Python :: 3.10
Classifier: Programming Language :: Python :: 3.11
Classifier: Programming Language :: Python :: 3.12
Classifier: Programming Language :: Python :: 3.13
Classifier: Programming Language :: Python :: 3.14
Classifier: Topic :: Documentation
Classifier: Topic :: Software Development :: Documentation
Requires-Python: >=3.10
Requires-Dist: defusedxml>=0.7.1
Requires-Dist: httpx>=0.24.0
Requires-Dist: mkdocs>=1.5.0
Requires-Dist: result>=0.17.0
